agor/__init__.py
agor/config.py
agor/constants.py
agor/exceptions.py
agor/git_binary.py
agor/logging.py
agor/main.py
agor/memory_sync.py
agor/platform.py
agor/repo_mgmt.py
agor/settings.py
agor/strategy.py
agor/utils.py
agor/validation.py
agor/version_check.py
agor/tools/AGOR_INSTRUCTIONS.md
agor/tools/AUGMENTCODE_LOCAL_DETECTION.md
agor/tools/AUGMENT_INITIALIZATION.md
agor/tools/BUNDLE_INITIALIZATION.md
agor/tools/BUNDLE_INSTRUCTIONS.md
agor/tools/CHAINABLE_PROMPTS.md
agor/tools/EXTERNAL_INTEGRATION_GUIDE.md
agor/tools/MENU_FLOW_GUIDE.md
agor/tools/MODE_DETECTION.md
agor/tools/PLATFORM_INITIALIZATION_PROMPTS.md
agor/tools/README_ai.md
agor/tools/REFRESH_PROTOCOLS.md
agor/tools/SNAPSHOT_SYSTEM_GUIDE.md
agor/tools/STANDALONE_INITIALIZATION.md
agor/tools/_commands.py
agor/tools/agent-requirements.txt
agor/tools/agent-start-here.md
agor/tools/agent_coordination.py
agor/tools/agent_prompt_templates.py
agor/tools/agent_prompts.py
agor/tools/agent_reference.py
agor/tools/agor-meta.md
agor/tools/agor_wrapper.py
agor/tools/checklist.py
agor/tools/code_exploration.py
agor/tools/code_exploration_docs.md
agor/tools/coordination-audit.md
agor/tools/coordination-example.md
agor/tools/dev_testing.py
agor/tools/dev_tools.py
agor/tools/external_integration.py
agor/tools/feedback_manager.py
agor/tools/git_operations.py
agor/tools/git_setup.py
agor/tools/hotkeys.py
agor/tools/index.md
agor/tools/memory_manager.py
agor/tools/meta-feedback-workflows.md
agor/tools/project_planning_templates.py
agor/tools/session-startup-checklist.md
agor/tools/snapshot_templates.py
agor/tools/snapshots.py
agor/tools/state-management.md
agor/tools/strategy_config.py
agor/tools/subprocess_manager.py
agor/tools/template_engine.py
agor/tools/work-orders-and-memory-guide.md
agor/tools/strategies/__init__.py
agor/tools/strategies/dependency_planning.py
agor/tools/strategies/error_optimization.py
agor/tools/strategies/mob_programming.py
agor/tools/strategies/multi_agent_strategies.py
agor-0.6.3.dist-info/licenses/LICENSE
agor-0.6.3.dist-info/METADATA
agor-0.6.3.dist-info/WHEEL
agor-0.6.3.dist-info/entry_points.txt
agor-0.6.3.dist-info/top_level.txt
agor-0.6.3.dist-info/RECORD
