Metadata-Version: 2.4
Name: agor
Version: 0.6.3
Summary: AgentOrchestrator - Multi-Agent Development Coordination Platform
Author-email: "Jeremiah K." <jeremiahk@gmx.com>
Project-URL: Bug Tracker, https://github.com/jeremiah-k/agor/issues
Project-URL: Repository, https://github.com/jeremiah-k/agor
Classifier: Programming Language :: Python :: 3
Classifier: License :: OSI Approved :: MIT License
Classifier: Operating System :: OS Independent
Classifier: Development Status :: 4 - Beta
Classifier: Topic :: Software Development :: Libraries :: Python Modules
Classifier: Topic :: Software Development :: Quality Assurance
Classifier: Intended Audience :: Developers
Requires-Python: >=3.10
License-File: LICENSE
Requires-Dist: httpx
Requires-Dist: plumbum
Requires-Dist: pyperclip
Requires-Dist: tqdm
Requires-Dist: typer
Requires-Dist: platformdirs<5.0.0,>=4.3.7
Requires-Dist: structlog>=24.1
Requires-Dist: pydantic-settings>=2.0
Requires-Dist: PyYAML
Provides-Extra: dev
Requires-Dist: pytest; extra == "dev"
Requires-Dist: pytest-cov; extra == "dev"
Requires-Dist: pytest-asyncio; extra == "dev"
Requires-Dist: pytest-tmp-git; extra == "dev"
Requires-Dist: ruff; extra == "dev"
Requires-Dist: mypy; extra == "dev"
Requires-Dist: pre-commit; extra == "dev"
Requires-Dist: build; extra == "dev"
Requires-Dist: twine; extra == "dev"
Dynamic: license-file
